{
  "fetched_at": "2026-04-29T12:12:41.988562Z",
  "source": "Collin County TX \u2013 PublicSearch",
  "date_range": {
    "from": "04/22/2026",
    "to": "04/29/2026"
  },
  "total": 71,
  "with_address": 71,
  "records": [
    {
      "doc_num": "2026000052600",
      "doc_type": "AJ",
      "filed": "2026-04-22",
      "cat": "judgment",
      "cat_label": "Abstract of Judgment",
      "owner": "EUBANKS STERLING",
      "grantee": "FIRST BUSINESS SPECIALTY FINANCE LLC",
      "amount": null,
      "legal": "N/A",
      "prop_address": "1708  PORT MILLSTONE TRL",
      "prop_city": "WYLIE",
      "prop_state": "TX",
      "prop_zip": "75098",
      "mail_address": "1708 PORT MILLSTONE TRL",
      "mail_city": "WYLIE",
      "mail_state": "TX",
      "mail_zip": "75098-0240",
      "clerk_url": "https://collin.tx.publicsearch.us/results?department=RP&_docTypes=AJ&recordedDateRange=20260422,20260429&searchType=advancedSearch",
      "flags": [
        "Judgment lien",
        "New this week"
      ],
      "score": 60,
      "_demo": false
    },
    {
      "doc_num": "2026000052954",
      "doc_type": "AJ",
      "filed": "2026-04-22",
      "cat": "judgment",
      "cat_label": "Abstract of Judgment",
      "owner": "MITCHELL SHIRLEY VALERIE",
      "grantee": "CREDIT UNION OF TEXAS",
      "amount": null,
      "legal": "N/A",
      "prop_address": "18424  WOODPOND PL",
      "prop_city": "DALLAS",
      "prop_state": "TX",
      "prop_zip": "75252",
      "mail_address": "18424 WOODPOND PL",
      "mail_city": "DALLAS",
      "mail_state": "TX",
      "mail_zip": "75252-7903",
      "clerk_url": "https://collin.tx.publicsearch.us/results?department=RP&_docTypes=AJ&recordedDateRange=20260422,20260429&searchType=advancedSearch",
      "flags": [
        "Judgment lien",
        "New this week"
      ],
      "score": 60,
      "_demo": false
    },
    {
      "doc_num": "2026000052504",
      "doc_type": "AJ",
      "filed": "2026-04-22",
      "cat": "judgment",
      "cat_label": "Abstract of Judgment",
      "owner": "WILLIS NOEMI",
      "grantee": "RED TARGET LLC",
      "amount": null,
      "legal": "N/A",
      "prop_address": "3025  PEARTREE LN",
      "prop_city": "CELINA",
      "prop_state": "TX",
      "prop_zip": "75009",
      "mail_address": "3025 PEARTREE LN",
      "mail_city": "CELINA",
      "mail_state": "TX",
      "mail_zip": "75009-2955",
      "clerk_url": "https://collin.tx.publicsearch.us/results?department=RP&_docTypes=AJ&recordedDateRange=20260422,20260429&searchType=advancedSearch",
      "flags": [
        "Judgment lien",
        "New this week"
      ],
      "score": 60,
      "_demo": false
    },
    {
      "doc_num": "2026000052562",
      "doc_type": "AJ",
      "filed": "2026-04-22",
      "cat": "judgment",
      "cat_label": "Abstract of Judgment",
      "owner": "NAYAK DEEPAK",
      "grantee": "TRUIST BANK",
      "amount": null,
      "legal": "N/A",
      "prop_address": "4601  KIPLING ST",
      "prop_city": "MCKINNEY",
      "prop_state": "TX",
      "prop_zip": "75071",
      "mail_address": "4601 KIPLING ST",
      "mail_city": "MCKINNEY",
      "mail_state": "TX",
      "mail_zip": "75071-5451",
      "clerk_url": "https://collin.tx.publicsearch.us/results?department=RP&_docTypes=AJ&recordedDateRange=20260422,20260429&searchType=advancedSearch",
      "flags": [
        "Judgment lien",
        "New this week"
      ],
      "score": 60,
      "_demo": false
    },
    {
      "doc_num": "2026000052707",
      "doc_type": "AH",
      "filed": "2026-04-22",
      "cat": "probate",
      "cat_label": "Affidavit of Heirship",
      "owner": "WASHINGTON LYMON",
      "grantee": "WINCHELL WILLIAM A DECEASED",
      "amount": null,
      "legal": "Subdivision - Name: BENT TREE WEST #5 DALLAS Lot: 22 Block: 22 Reference - G/290",
      "prop_address": "4359  HIGHLANDER DR",
      "prop_city": "DALLAS",
      "prop_state": "TX",
      "prop_zip": "75287",
      "mail_address": "4359 HIGHLANDER DR",
      "mail_city": "DALLAS",
      "mail_state": "TX",
      "mail_zip": "75287-6842",
      "clerk_url": "https://collin.tx.publicsearch.us/results?department=RP&_docTypes=AH&recordedDateRange=20260422,20260429&searchType=advancedSearch",
      "flags": [
        "Probate / estate",
        "New this week"
      ],
      "score": 60,
      "_demo": false
    },
    {
      "doc_num": "2026000052384",
      "doc_type": "LIEN",
      "filed": "2026-04-22",
      "cat": "lien",
      "cat_label": "Lien",
      "owner": "SHAIKH ADNAN A",
      "grantee": "TWIN CREEKS COMMUNITY ASN INC",
      "amount": null,
      "legal": "Subdivision - Name: ESTATES TWIN CREEKS #1 AMND ALLEN Lot: 20 Block: D Reference - 2008/157",
      "prop_address": "620  HIDDEN COVE DR",
      "prop_city": "PRINCETON",
      "prop_state": "TX",
      "prop_zip": "75407",
      "mail_address": "620 HIDDEN COVE DR",
      "mail_city": "PRINCETON",
      "mail_state": "TX",
      "mail_zip": "75407-2919",
      "clerk_url": "https://collin.tx.publicsearch.us/results?department=RP&_docTypes=LIEN&recordedDateRange=20260422,20260429&searchType=advancedSearch",
      "flags": [
        "Lien",
        "New this week"
      ],
      "score": 60,
      "_demo": false
    },
    {
      "doc_num": "2026000052856",
      "doc_type": "LIEN",
      "filed": "2026-04-22",
      "cat": "lien",
      "cat_label": "Lien",
      "owner": "ASKEW KYLE",
      "grantee": "HAYS CLINT ATTORNEY",
      "amount": null,
      "legal": "Subdivision - Name: VENETIAN WESTON #1 Lot: 17 Block: BB Reference - 2022/237",
      "prop_address": "1720  BARNWOOD TRCE",
      "prop_city": "CELINA",
      "prop_state": "TX",
      "prop_zip": "75009",
      "mail_address": "1720 BARNWOOD TRCE",
      "mail_city": "WESTON",
      "mail_state": "TX",
      "mail_zip": "75097",
      "clerk_url": "https://collin.tx.publicsearch.us/results?department=RP&_docTypes=LIEN&recordedDateRange=20260422,20260429&searchType=advancedSearch",
      "flags": [
        "Lien",
        "New this week"
      ],
      "score": 60,
      "_demo": false
    },
    {
      "doc_num": "2026000052897",
      "doc_type": "LIEN",
      "filed": "2026-04-22",
      "cat": "lien",
      "cat_label": "Lien",
      "owner": "SELWYN CHRISTOPHER",
      "grantee": "HAYS CLINT ATTORNEY",
      "amount": null,
      "legal": "Subdivision - Unit or Part: 23",
      "prop_address": "216  GRIFFITH DR",
      "prop_city": "PRINCETON",
      "prop_state": "TX",
      "prop_zip": "75407",
      "mail_address": "216 GRIFFITH DR",
      "mail_city": "PRINCETON",
      "mail_state": "TX",
      "mail_zip": "75407-3181",
      "clerk_url": "https://collin.tx.publicsearch.us/results?department=RP&_docTypes=LIEN&recordedDateRange=20260422,20260429&searchType=advancedSearch",
      "flags": [
        "Lien",
        "New this week"
      ],
      "score": 60,
      "_demo": false
    },
    {
      "doc_num": "2026000052855",
      "doc_type": "LIEN",
      "filed": "2026-04-22",
      "cat": "lien",
      "cat_label": "Lien",
      "owner": "GARVIN LASHUNDRA",
      "grantee": "HAYS CLINT ATTORNEY",
      "amount": null,
      "legal": "Subdivision - Name: BOZMAN FARM ESTATES #7 WYLIE Lot: 6 Block: C Reference - 2019/766",
      "prop_address": "1601  ANACUA LN",
      "prop_city": "WYLIE",
      "prop_state": "TX",
      "prop_zip": "75098",
      "mail_address": "1601 ANACUA LN",
      "mail_city": "WYLIE",
      "mail_state": "TX",
      "mail_zip": "75098-1698",
      "clerk_url": "https://collin.tx.publicsearch.us/results?department=RP&_docTypes=LIEN&recordedDateRange=20260422,20260429&searchType=advancedSearch",
      "flags": [
        "Lien",
        "New this week"
      ],
      "score": 60,
      "_demo": false
    },
    {
      "doc_num": "2026000052857",
      "doc_type": "LIEN",
      "filed": "2026-04-22",
      "cat": "lien",
      "cat_label": "Lien",
      "owner": "TONGWA HONORINE",
      "grantee": "VENETIAN LAGUNA AZURE HOMEOWNERS ASN INC",
      "amount": null,
      "legal": "Subdivision - Name: VENETIAN WESTON #1 Lot: 10 Block: CC Reference - 2022/237",
      "prop_address": "1636  OPEN RANGE RD",
      "prop_city": "CELINA",
      "prop_state": "TX",
      "prop_zip": "75009",
      "mail_address": "17228 EASTBROOK DR",
      "mail_city": "CELINA",
      "mail_state": "TX",
      "mail_zip": "75009-2099",
      "clerk_url": "https://collin.tx.publicsearch.us/results?department=RP&_docTypes=LIEN&recordedDateRange=20260422,20260429&searchType=advancedSearch",
      "flags": [
        "Lien",
        "New this week"
      ],
      "score": 60,
      "_demo": false
    },
    {
      "doc_num": "2026000052859",
      "doc_type": "LIEN",
      "filed": "2026-04-22",
      "cat": "lien",
      "cat_label": "Lien",
      "owner": "HUFFSTETLER CRAIG",
      "grantee": "BOZMAN FARM ESTATES MASTER ASN INC",
      "amount": null,
      "legal": "Subdivision - Name: LAKE TRAILS BOZMAN FARM WYLIE Lot: 19 Block: C Reference - P/565",
      "prop_address": "1319  HILL VIEW TRL",
      "prop_city": "WYLIE",
      "prop_state": "TX",
      "prop_zip": "75098",
      "mail_address": "1319 HILL VIEW TRL",
      "mail_city": "WYLIE",
      "mail_state": "TX",
      "mail_zip": "75098-6657",
      "clerk_url": "https://collin.tx.publicsearch.us/results?department=RP&_docTypes=LIEN&recordedDateRange=20260422,20260429&searchType=advancedSearch",
      "flags": [
        "Lien",
        "New this week"
      ],
      "score": 60,
      "_demo": false
    },
    {
      "doc_num": "2026000052854",
      "doc_type": "LIEN",
      "filed": "2026-04-22",
      "cat": "lien",
      "cat_label": "Lien",
      "owner": "SPANGLER ESMERALDA YOLANDA",
      "grantee": "ELEVON HOMEOWNERS ASN INC B481",
      "amount": null,
      "legal": "Subdivision - Name: ELEVON PHASE 1A COLLIN 2022 676-679 Lot: 1 Block: E Reference - 2022/676",
      "prop_address": "600  DAYBREAK LN",
      "prop_city": "LAVON",
      "prop_state": "TX",
      "prop_zip": "75166",
      "mail_address": "600 DAYBREAK LN",
      "mail_city": "LAVON",
      "mail_state": "TX",
      "mail_zip": "75166-1993",
      "clerk_url": "https://collin.tx.publicsearch.us/results?department=RP&_docTypes=LIEN&recordedDateRange=20260422,20260429&searchType=advancedSearch",
      "flags": [
        "Lien",
        "New this week"
      ],
      "score": 60,
      "_demo": false
    },
    {
      "doc_num": "2026000052930",
      "doc_type": "ML",
      "filed": "2026-04-22",
      "cat": "lien",
      "cat_label": "Mechanics Lien",
      "owner": "DUFFY RYAN",
      "grantee": "FROST BANK",
      "amount": null,
      "legal": "Subdivision - Name: TUCKER HILL #4 MCKINNEY Lot: 11 Block: Y Reference - 2017/527",
      "prop_address": "7313  STANHOPE ST",
      "prop_city": "MCKINNEY",
      "prop_state": "TX",
      "prop_zip": "75071",
      "mail_address": "7313 STANHOPE ST",
      "mail_city": "MCKINNEY",
      "mail_state": "TX",
      "mail_zip": "75071-1559",
      "clerk_url": "https://collin.tx.publicsearch.us/results?department=RP&_docTypes=ML&recordedDateRange=20260422,20260429&searchType=advancedSearch",
      "flags": [
        "Mechanic lien",
        "New this week"
      ],
      "score": 60,
      "_demo": false
    },
    {
      "doc_num": "2026000053419",
      "doc_type": "FTL",
      "filed": "2026-04-23",
      "cat": "lien",
      "cat_label": "Federal Tax Lien",
      "owner": "MURRAY DANIEL LEWIS",
      "grantee": "U S A INTERNAL REVENUE SERVICE",
      "amount": null,
      "legal": "N/A",
      "prop_address": "5905  MILANO DR",
      "prop_city": "PLANO",
      "prop_state": "TX",
      "prop_zip": "75093",
      "mail_address": "5905 MILANO DR",
      "mail_city": "PLANO",
      "mail_state": "TX",
      "mail_zip": "75093-7082",
      "clerk_url": "https://collin.tx.publicsearch.us/results?department=RP&_docTypes=FTL&recordedDateRange=20260422,20260429&searchType=advancedSearch",
      "flags": [
        "Tax lien",
        "New this week"
      ],
      "score": 60,
      "_demo": false
    },
    {
      "doc_num": "2026000053087",
      "doc_type": "AJ",
      "filed": "2026-04-23",
      "cat": "judgment",
      "cat_label": "Abstract of Judgment",
      "owner": "DIAMOND JONATHAN BLAKE",
      "grantee": "DIAMOND TRACI RENE",
      "amount": null,
      "legal": "N/A",
      "prop_address": "3301  SKI LIFT CT",
      "prop_city": "MCKINNEY",
      "prop_state": "TX",
      "prop_zip": "75070",
      "mail_address": "3301 SKI LIFT CT",
      "mail_city": "MCKINNEY",
      "mail_state": "TX",
      "mail_zip": "75070-6006",
      "clerk_url": "https://collin.tx.publicsearch.us/results?department=RP&_docTypes=AJ&recordedDateRange=20260422,20260429&searchType=advancedSearch",
      "flags": [
        "Judgment lien",
        "New this week"
      ],
      "score": 60,
      "_demo": false
    },
    {
      "doc_num": "2026000053088",
      "doc_type": "AJ",
      "filed": "2026-04-23",
      "cat": "judgment",
      "cat_label": "Abstract of Judgment",
      "owner": "DIAMOND JONATHAN BLAKE",
      "grantee": "DIAMOND TRACI RENE",
      "amount": null,
      "legal": "N/A",
      "prop_address": "3301  SKI LIFT CT",
      "prop_city": "MCKINNEY",
      "prop_state": "TX",
      "prop_zip": "75070",
      "mail_address": "3301 SKI LIFT CT",
      "mail_city": "MCKINNEY",
      "mail_state": "TX",
      "mail_zip": "75070-6006",
      "clerk_url": "https://collin.tx.publicsearch.us/results?department=RP&_docTypes=AJ&recordedDateRange=20260422,20260429&searchType=advancedSearch",
      "flags": [
        "Judgment lien",
        "New this week"
      ],
      "score": 60,
      "_demo": false
    },
    {
      "doc_num": "2026000053279",
      "doc_type": "AJ",
      "filed": "2026-04-23",
      "cat": "judgment",
      "cat_label": "Abstract of Judgment",
      "owner": "WALLACE WALTER",
      "grantee": "SCIL TEXAS LLC",
      "amount": null,
      "legal": "N/A",
      "prop_address": "1580  LYNN LN",
      "prop_city": "LUCAS",
      "prop_state": "TX",
      "prop_zip": "75002",
      "mail_address": "1580 LYNN LN",
      "mail_city": "ALLEN",
      "mail_state": "TX",
      "mail_zip": "75002-8047",
      "clerk_url": "https://collin.tx.publicsearch.us/results?department=RP&_docTypes=AJ&recordedDateRange=20260422,20260429&searchType=advancedSearch",
      "flags": [
        "Judgment lien",
        "New this week"
      ],
      "score": 60,
      "_demo": false
    },
    {
      "doc_num": "2026000053060",
      "doc_type": "AH",
      "filed": "2026-04-23",
      "cat": "probate",
      "cat_label": "Affidavit of Heirship",
      "owner": "SEYB KATHERINE",
      "grantee": "CAMPBELL HENRY CARLISLE DECEASED",
      "amount": null,
      "legal": "Subdivision - Name: WREN CREEK ADDN #2B MCK Lot: 6 Block: F Reference - 2007/115",
      "prop_address": "7304  MAUDSLEY DR",
      "prop_city": "MCKINNEY",
      "prop_state": "TX",
      "prop_zip": "75071",
      "mail_address": "7304 MAUDSLEY DR",
      "mail_city": "MCKINNEY",
      "mail_state": "TX",
      "mail_zip": "75071-4796",
      "clerk_url": "https://collin.tx.publicsearch.us/results?department=RP&_docTypes=AH&recordedDateRange=20260422,20260429&searchType=advancedSearch",
      "flags": [
        "Probate / estate",
        "New this week"
      ],
      "score": 60,
      "_demo": false
    },
    {
      "doc_num": "2026000053385",
      "doc_type": "AH",
      "filed": "2026-04-23",
      "cat": "probate",
      "cat_label": "Affidavit of Heirship",
      "owner": "COHAN STEVEN LEE",
      "grantee": "COHAN VIVIAN THERESA DECEASED",
      "amount": null,
      "legal": "Subdivision - Name: WYNDFIELD MCKINNEY Lot: 11 Block: D Reference - K/500",
      "prop_address": "2202  SPRUCE CIR",
      "prop_city": "MCKINNEY",
      "prop_state": "TX",
      "prop_zip": "75071",
      "mail_address": "2202 SPRUCE CIR",
      "mail_city": "MCKINNEY",
      "mail_state": "TX",
      "mail_zip": "75071-2881",
      "clerk_url": "https://collin.tx.publicsearch.us/results?department=RP&_docTypes=AH&recordedDateRange=20260422,20260429&searchType=advancedSearch",
      "flags": [
        "Probate / estate",
        "New this week"
      ],
      "score": 60,
      "_demo": false
    },
    {
      "doc_num": "2026000053195",
      "doc_type": "LIEN",
      "filed": "2026-04-23",
      "cat": "lien",
      "cat_label": "Lien",
      "owner": "FELDER JONATHAN J",
      "grantee": "MARTIN ANTONIO AGENT",
      "amount": null,
      "legal": "Subdivision - Name: BENT TRAIL #4 DALLAS Lot: 1 Block: 16 Reference - F/294",
      "prop_address": "18424  RAIN DANCE TRL",
      "prop_city": "DALLAS",
      "prop_state": "TX",
      "prop_zip": "75252",
      "mail_address": "18424 RAIN DANCE TRL",
      "mail_city": "DALLAS",
      "mail_state": "TX",
      "mail_zip": "75252-7901",
      "clerk_url": "https://collin.tx.publicsearch.us/results?department=RP&_docTypes=LIEN&recordedDateRange=20260422,20260429&searchType=advancedSearch",
      "flags": [
        "Lien",
        "New this week"
      ],
      "score": 60,
      "_demo": false
    },
    {
      "doc_num": "2026000053217",
      "doc_type": "LIEN",
      "filed": "2026-04-23",
      "cat": "lien",
      "cat_label": "Lien",
      "owner": "STURDIVANT CARRIE",
      "grantee": "LANDSCAPE ASN OF BENT TRAIL PHASE 4 INC",
      "amount": null,
      "legal": "Subdivision - Name: BENT TRAIL #4 DALLAS Lot: 15 Block: 16 Reference - F/294",
      "prop_address": "6042  BENTWOOD CT",
      "prop_city": "DALLAS",
      "prop_state": "TX",
      "prop_zip": "75252",
      "mail_address": "6042 BENTWOOD CT",
      "mail_city": "DALLAS",
      "mail_state": "TX",
      "mail_zip": "75252-5100",
      "clerk_url": "https://collin.tx.publicsearch.us/results?department=RP&_docTypes=LIEN&recordedDateRange=20260422,20260429&searchType=advancedSearch",
      "flags": [
        "Lien",
        "New this week"
      ],
      "score": 60,
      "_demo": false
    },
    {
      "doc_num": "2026000053283",
      "doc_type": "LIEN",
      "filed": "2026-04-23",
      "cat": "lien",
      "cat_label": "Lien",
      "owner": "ELIZONDO GENARA C",
      "grantee": "PLANO CITY OF",
      "amount": null,
      "legal": "Subdivision - Name: ARMSTRONG PARK #3 PLANO Lot: 8 Block: 5 Reference - 6/68",
      "prop_address": "2300  RICHMOND DR",
      "prop_city": "PLANO",
      "prop_state": "TX",
      "prop_zip": "75074",
      "mail_address": "2300 RICHMOND DR",
      "mail_city": "PLANO",
      "mail_state": "TX",
      "mail_zip": "75074-5028",
      "clerk_url": "https://collin.tx.publicsearch.us/results?department=RP&_docTypes=LIEN&recordedDateRange=20260422,20260429&searchType=advancedSearch",
      "flags": [
        "Lien",
        "New this week"
      ],
      "score": 60,
      "_demo": false
    },
    {
      "doc_num": "2026000053613",
      "doc_type": "LIEN",
      "filed": "2026-04-23",
      "cat": "lien",
      "cat_label": "Lien",
      "owner": "CRP SCP MCKINNEY OWNER LP",
      "grantee": "FUNGI ENVIRONMENTAL LLC",
      "amount": null,
      "legal": "Subdivision - Name: MERIDIAN SOUTHGATE MCKINNEY Lot: 2R2 Block: A Reference - 2020/317",
      "prop_address": "132  MILL ST",
      "prop_city": "ANNA",
      "prop_state": "TX",
      "prop_zip": "75409",
      "mail_address": "2875 W RAY RD STE 6-430-34788",
      "mail_city": "CHANDLER",
      "mail_state": "AZ",
      "mail_zip": "85224-3524",
      "clerk_url": "https://collin.tx.publicsearch.us/results?department=RP&_docTypes=LIEN&recordedDateRange=20260422,20260429&searchType=advancedSearch",
      "flags": [
        "Lien",
        "New this week"
      ],
      "score": 60,
      "_demo": false
    },
    {
      "doc_num": "2026000053282",
      "doc_type": "LIEN",
      "filed": "2026-04-23",
      "cat": "lien",
      "cat_label": "Lien",
      "owner": "ELIZONDO GENARA C",
      "grantee": "PLANO CITY OF",
      "amount": null,
      "legal": "Subdivision - Name: ARMSTRONG PARK #3 PLANO Lot: 8 Block: 5 Reference - 6/68",
      "prop_address": "2300  RICHMOND DR",
      "prop_city": "PLANO",
      "prop_state": "TX",
      "prop_zip": "75074",
      "mail_address": "2300 RICHMOND DR",
      "mail_city": "PLANO",
      "mail_state": "TX",
      "mail_zip": "75074-5028",
      "clerk_url": "https://collin.tx.publicsearch.us/results?department=RP&_docTypes=LIEN&recordedDateRange=20260422,20260429&searchType=advancedSearch",
      "flags": [
        "Lien",
        "New this week"
      ],
      "score": 60,
      "_demo": false
    },
    {
      "doc_num": "2026000053182",
      "doc_type": "LIEN",
      "filed": "2026-04-23",
      "cat": "lien",
      "cat_label": "Lien",
      "owner": "TAKAKUWA RYO",
      "grantee": "MARTIN ANTONIO AGENT",
      "amount": null,
      "legal": "Subdivision - Name: BENT TRAIL #4 DALLAS Lot: 27 Block: 13 Reference - F/294",
      "prop_address": "6223  BENTWOOD TRL",
      "prop_city": "DALLAS",
      "prop_state": "TX",
      "prop_zip": "75252",
      "mail_address": "6223 BENTWOOD TRL",
      "mail_city": "DALLAS",
      "mail_state": "TX",
      "mail_zip": "75252-5151",
      "clerk_url": "https://collin.tx.publicsearch.us/results?department=RP&_docTypes=LIEN&recordedDateRange=20260422,20260429&searchType=advancedSearch",
      "flags": [
        "Lien",
        "New this week"
      ],
      "score": 60,
      "_demo": false
    },
    {
      "doc_num": "2026000053524",
      "doc_type": "LIEN",
      "filed": "2026-04-23",
      "cat": "lien",
      "cat_label": "Lien",
      "owner": "GANPATH SHOPANA",
      "grantee": "HAYS CLINT ATTORNEY",
      "amount": null,
      "legal": "Subdivision - Name: VENETIAN WESTON #1 Lot: 13 Block: DD Reference - 2022/237",
      "prop_address": "720  RUSTY SPURS PL",
      "prop_city": "CELINA",
      "prop_state": "TX",
      "prop_zip": "75009",
      "mail_address": "720 RUSTY SPURS PL",
      "mail_city": "WESTON",
      "mail_state": "TX",
      "mail_zip": "75097",
      "clerk_url": "https://collin.tx.publicsearch.us/results?department=RP&_docTypes=LIEN&recordedDateRange=20260422,20260429&searchType=advancedSearch",
      "flags": [
        "Lien",
        "New this week"
      ],
      "score": 60,
      "_demo": false
    },
    {
      "doc_num": "2026000053754",
      "doc_type": "STL",
      "filed": "2026-04-24",
      "cat": "lien",
      "cat_label": "State Tax Lien",
      "owner": "MOCK MARIA SARAH",
      "grantee": "TEXAS STATE OF",
      "amount": null,
      "legal": "N/A",
      "prop_address": "2513  CUSTER PKWY",
      "prop_city": "RICHARDSON",
      "prop_state": "TX",
      "prop_zip": "75080",
      "mail_address": "2513 CUSTER PKWY",
      "mail_city": "RICHARDSON",
      "mail_state": "TX",
      "mail_zip": "75080-2121",
      "clerk_url": "https://collin.tx.publicsearch.us/results?department=RP&_docTypes=STL&recordedDateRange=20260422,20260429&searchType=advancedSearch",
      "flags": [
        "Tax lien",
        "New this week"
      ],
      "score": 60,
      "_demo": false
    },
    {
      "doc_num": "2026000053794",
      "doc_type": "AJ",
      "filed": "2026-04-24",
      "cat": "judgment",
      "cat_label": "Abstract of Judgment",
      "owner": "TERRY WILLIAM",
      "grantee": "CAPITAL ONE NA",
      "amount": null,
      "legal": "N/A",
      "prop_address": "3316  SEQUOIA LN",
      "prop_city": "MELISSA",
      "prop_state": "TX",
      "prop_zip": "75454",
      "mail_address": "3316 SEQUOIA LN",
      "mail_city": "MELISSA",
      "mail_state": "TX",
      "mail_zip": "75454-0450",
      "clerk_url": "https://collin.tx.publicsearch.us/results?department=RP&_docTypes=AJ&recordedDateRange=20260422,20260429&searchType=advancedSearch",
      "flags": [
        "Judgment lien",
        "New this week"
      ],
      "score": 60,
      "_demo": false
    },
    {
      "doc_num": "2026000053742",
      "doc_type": "AJ",
      "filed": "2026-04-24",
      "cat": "judgment",
      "cat_label": "Abstract of Judgment",
      "owner": "SMITH MICHAEL D",
      "grantee": "CAPITAL ONE BANK USA NA",
      "amount": null,
      "legal": "N/A",
      "prop_address": "1988  BAR HARBOR DR",
      "prop_city": "ALLEN",
      "prop_state": "TX",
      "prop_zip": "75013",
      "mail_address": "1988 BAR HARBOR DR",
      "mail_city": "ALLEN",
      "mail_state": "TX",
      "mail_zip": "75013-3079",
      "clerk_url": "https://collin.tx.publicsearch.us/results?department=RP&_docTypes=AJ&recordedDateRange=20260422,20260429&searchType=advancedSearch",
      "flags": [
        "Judgment lien",
        "New this week"
      ],
      "score": 60,
      "_demo": false
    },
    {
      "doc_num": "2026000054335",
      "doc_type": "AH",
      "filed": "2026-04-24",
      "cat": "probate",
      "cat_label": "Affidavit of Heirship",
      "owner": "MATZKE JOAN CAROLYN",
      "grantee": "MATZKE RONALD LEROY DECEASED",
      "amount": null,
      "legal": "Subdivision - Name: STANFORD MEADOW #1 MCK Lot: 6 Block: A Reference - L/913",
      "prop_address": "7500  SUMMER GLEN DR",
      "prop_city": "MCKINNEY",
      "prop_state": "TX",
      "prop_zip": "75072",
      "mail_address": "2105 MILLWALL DR",
      "mail_city": "MCKINNEY",
      "mail_state": "TX",
      "mail_zip": "75071-4412",
      "clerk_url": "https://collin.tx.publicsearch.us/results?department=RP&_docTypes=AH&recordedDateRange=20260422,20260429&searchType=advancedSearch",
      "flags": [
        "Probate / estate",
        "New this week"
      ],
      "score": 60,
      "_demo": false
    },
    {
      "doc_num": "2026000053936",
      "doc_type": "AH",
      "filed": "2026-04-24",
      "cat": "probate",
      "cat_label": "Affidavit of Heirship",
      "owner": "DUPONT HELEN",
      "grantee": "HAROUTUNIAN MEHRDAD DECEASED",
      "amount": null,
      "legal": "Subdivision - Name: WEST PLANO EST #3 Lot: 41 Block: 4 Reference - C/164",
      "prop_address": "3304  CANYON VALLEY TRL",
      "prop_city": "PLANO",
      "prop_state": "TX",
      "prop_zip": "75023",
      "mail_address": "3304 CANYON VALLEY TRL",
      "mail_city": "PLANO",
      "mail_state": "TX",
      "mail_zip": "75023-7806",
      "clerk_url": "https://collin.tx.publicsearch.us/results?department=RP&_docTypes=AH&recordedDateRange=20260422,20260429&searchType=advancedSearch",
      "flags": [
        "Probate / estate",
        "New this week"
      ],
      "score": 60,
      "_demo": false
    },
    {
      "doc_num": "2026000054123",
      "doc_type": "AH",
      "filed": "2026-04-24",
      "cat": "probate",
      "cat_label": "Affidavit of Heirship",
      "owner": "COHEN ROSIE",
      "grantee": "MCELROY JUDITH DECEASED ESTATE",
      "amount": null,
      "legal": "N/A",
      "prop_address": "2205  PHEASANT RUN RD",
      "prop_city": "PLANO",
      "prop_state": "TX",
      "prop_zip": "75023",
      "mail_address": "2205 PHEASANT RUN RD",
      "mail_city": "PLANO",
      "mail_state": "TX",
      "mail_zip": "75023-1606",
      "clerk_url": "https://collin.tx.publicsearch.us/results?department=RP&_docTypes=AH&recordedDateRange=20260422,20260429&searchType=advancedSearch",
      "flags": [
        "Probate / estate",
        "New this week"
      ],
      "score": 60,
      "_demo": false
    },
    {
      "doc_num": "2026000053938",
      "doc_type": "AH",
      "filed": "2026-04-24",
      "cat": "probate",
      "cat_label": "Affidavit of Heirship",
      "owner": "MCNEASE BRENDA",
      "grantee": "HAROUTUNIAN MEHRDAD DECEASED",
      "amount": null,
      "legal": "Subdivision - Name: WEST PLANO EST #3 Lot: 41 Block: 4 Reference - C/164",
      "prop_address": "906  THOREAU LN",
      "prop_city": "ALLEN",
      "prop_state": "TX",
      "prop_zip": "75002",
      "mail_address": "906 THOREAU LN",
      "mail_city": "ALLEN",
      "mail_state": "TX",
      "mail_zip": "75002-2004",
      "clerk_url": "https://collin.tx.publicsearch.us/results?department=RP&_docTypes=AH&recordedDateRange=20260422,20260429&searchType=advancedSearch",
      "flags": [
        "Probate / estate",
        "New this week"
      ],
      "score": 60,
      "_demo": false
    },
    {
      "doc_num": "2026000053944",
      "doc_type": "LIEN",
      "filed": "2026-04-24",
      "cat": "lien",
      "cat_label": "Lien",
      "owner": "HOLLMAN MICHAEL",
      "grantee": "CELINA CARTER RANCH HOMEOWNERS ASN INC",
      "amount": null,
      "legal": "Subdivision - Name: CARTER RANCH #1 CELINA Lot: 10 Block: U Reference - P/372",
      "prop_address": "318  TARPAN TRL",
      "prop_city": "CELINA",
      "prop_state": "TX",
      "prop_zip": "75009",
      "mail_address": "318 TARPAN TRL",
      "mail_city": "CELINA",
      "mail_state": "TX",
      "mail_zip": "75009-4607",
      "clerk_url": "https://collin.tx.publicsearch.us/results?department=RP&_docTypes=LIEN&recordedDateRange=20260422,20260429&searchType=advancedSearch",
      "flags": [
        "Lien",
        "New this week"
      ],
      "score": 60,
      "_demo": false
    },
    {
      "doc_num": "2026000053907",
      "doc_type": "LIEN",
      "filed": "2026-04-24",
      "cat": "lien",
      "cat_label": "Lien",
      "owner": "URBAN JEFFREY",
      "grantee": "ALLEN CITY OF",
      "amount": null,
      "legal": "Subdivision - Name: HERITAGE PARK #1 ALLEN Lot: 13 Block: 2 Reference - F/768",
      "prop_address": "753  LIVINGSTON DR",
      "prop_city": "ALLEN",
      "prop_state": "TX",
      "prop_zip": "75002",
      "mail_address": "753 LIVINGSTON DR",
      "mail_city": "ALLEN",
      "mail_state": "TX",
      "mail_zip": "75002-5229",
      "clerk_url": "https://collin.tx.publicsearch.us/results?department=RP&_docTypes=LIEN&recordedDateRange=20260422,20260429&searchType=advancedSearch",
      "flags": [
        "Lien",
        "New this week"
      ],
      "score": 60,
      "_demo": false
    },
    {
      "doc_num": "2026000053683",
      "doc_type": "LIEN",
      "filed": "2026-04-24",
      "cat": "lien",
      "cat_label": "Lien",
      "owner": "REEDY LANCE V",
      "grantee": "BIRMINGHAM HOMEOWNERS ASN",
      "amount": null,
      "legal": "Subdivision - Name: BIRMINGHAM FARMS 2A WYL Lot: 20 Block: M Reference - N/887",
      "prop_address": "604  GUNTERS MOUNTAIN LN",
      "prop_city": "WYLIE",
      "prop_state": "TX",
      "prop_zip": "75098",
      "mail_address": "604 GUNTERS MOUNTAIN LN",
      "mail_city": "WYLIE",
      "mail_state": "TX",
      "mail_zip": "75098-6900",
      "clerk_url": "https://collin.tx.publicsearch.us/results?department=RP&_docTypes=LIEN&recordedDateRange=20260422,20260429&searchType=advancedSearch",
      "flags": [
        "Lien",
        "New this week"
      ],
      "score": 60,
      "_demo": false
    },
    {
      "doc_num": "2026000054288",
      "doc_type": "LIEN",
      "filed": "2026-04-24",
      "cat": "lien",
      "cat_label": "Lien",
      "owner": "RAHMAN MAYEEDUR",
      "grantee": "EXTERIOR PROSTAR LLC",
      "amount": null,
      "legal": "Subdivision - Name: HIGHLANDS OF PRESTON RIDGE 3 Lot: 6 Block: C",
      "prop_address": "4521  BRIAR HOLLOW DR",
      "prop_city": "PLANO",
      "prop_state": "TX",
      "prop_zip": "75093",
      "mail_address": "4521 BRIAR HOLLOW DR",
      "mail_city": "PLANO",
      "mail_state": "TX",
      "mail_zip": "75093-3341",
      "clerk_url": "https://collin.tx.publicsearch.us/results?department=RP&_docTypes=LIEN&recordedDateRange=20260422,20260429&searchType=advancedSearch",
      "flags": [
        "Lien",
        "New this week"
      ],
      "score": 60,
      "_demo": false
    },
    {
      "doc_num": "2026000054428",
      "doc_type": "STL",
      "filed": "2026-04-27",
      "cat": "lien",
      "cat_label": "State Tax Lien",
      "owner": "PATEL ILESH H",
      "grantee": "TEXAS STATE OF",
      "amount": null,
      "legal": "N/A",
      "prop_address": "300  SYCAMORE DR",
      "prop_city": "MURPHY",
      "prop_state": "TX",
      "prop_zip": "75094",
      "mail_address": "300 SYCAMORE DR",
      "mail_city": "MURPHY",
      "mail_state": "TX",
      "mail_zip": "75094-3540",
      "clerk_url": "https://collin.tx.publicsearch.us/results?department=RP&_docTypes=STL&recordedDateRange=20260422,20260429&searchType=advancedSearch",
      "flags": [
        "Tax lien",
        "New this week"
      ],
      "score": 60,
      "_demo": false
    },
    {
      "doc_num": "2026000054624",
      "doc_type": "PROB",
      "filed": "2026-04-27",
      "cat": "probate",
      "cat_label": "Probate",
      "owner": "JABLONSKI PATRICIA A DECEASED ESTATE",
      "grantee": "PUBLIC",
      "amount": null,
      "legal": "N/A",
      "prop_address": "7504  SHASTA DR",
      "prop_city": "MCKINNEY",
      "prop_state": "TX",
      "prop_zip": "75071",
      "mail_address": "7504 SHASTA DR",
      "mail_city": "MCKINNEY",
      "mail_state": "TX",
      "mail_zip": "75071-7460",
      "clerk_url": "https://collin.tx.publicsearch.us/results?department=RP&_docTypes=PROB&recordedDateRange=20260422,20260429&searchType=advancedSearch",
      "flags": [
        "Probate / estate",
        "New this week"
      ],
      "score": 60,
      "_demo": false
    },
    {
      "doc_num": "2026000054663",
      "doc_type": "PROB",
      "filed": "2026-04-27",
      "cat": "probate",
      "cat_label": "Probate",
      "owner": "BASCOU TODD ALAN DECEASED ESTATE",
      "grantee": "PUBLIC",
      "amount": null,
      "legal": "Subdivision - Name: RUSSELL CREEK 1 PLANO Lot: 2 Block: A Reference - C/636",
      "prop_address": "1433  CUMBERLAND TRL",
      "prop_city": "PLANO",
      "prop_state": "TX",
      "prop_zip": "75023",
      "mail_address": "1314 VINA DEL MAR AVE",
      "mail_city": "PLACENTIA",
      "mail_state": "CA",
      "mail_zip": "92870-3937",
      "clerk_url": "https://collin.tx.publicsearch.us/results?department=RP&_docTypes=PROB&recordedDateRange=20260422,20260429&searchType=advancedSearch",
      "flags": [
        "Probate / estate",
        "New this week"
      ],
      "score": 60,
      "_demo": false
    },
    {
      "doc_num": "2026000054886",
      "doc_type": "AH",
      "filed": "2026-04-27",
      "cat": "probate",
      "cat_label": "Affidavit of Heirship",
      "owner": "JONES EARNESTINE",
      "grantee": "RHODES ROBERT L DECEASED",
      "amount": null,
      "legal": "Subdivision - Name: CELINA ORIGINAL DONATION Lot: 12 Block: 60 Reference - 1/114",
      "prop_address": "412 E ASH ST",
      "prop_city": "CELINA",
      "prop_state": "TX",
      "prop_zip": "75009",
      "mail_address": "412 E ASH ST",
      "mail_city": "CELINA",
      "mail_state": "TX",
      "mail_zip": "75009-6390",
      "clerk_url": "https://collin.tx.publicsearch.us/results?department=RP&_docTypes=AH&recordedDateRange=20260422,20260429&searchType=advancedSearch",
      "flags": [
        "Probate / estate",
        "New this week"
      ],
      "score": 60,
      "_demo": false
    },
    {
      "doc_num": "2026000054885",
      "doc_type": "AH",
      "filed": "2026-04-27",
      "cat": "probate",
      "cat_label": "Affidavit of Heirship",
      "owner": "ANDREWS LAURA",
      "grantee": "HASKELL-VARNER LOURISSIA RHODES DECEASED",
      "amount": null,
      "legal": "Subdivision - Name: CELINA ORIGINAL DONATION Lot: 12 Block: 60 Reference - 1/114",
      "prop_address": "3500  VAN ZANDT RD",
      "prop_city": "MELISSA",
      "prop_state": "TX",
      "prop_zip": "75454",
      "mail_address": "3500 VAN ZANDT RD",
      "mail_city": "MELISSA",
      "mail_state": "TX",
      "mail_zip": "75454-2106",
      "clerk_url": "https://collin.tx.publicsearch.us/results?department=RP&_docTypes=AH&recordedDateRange=20260422,20260429&searchType=advancedSearch",
      "flags": [
        "Probate / estate",
        "New this week"
      ],
      "score": 60,
      "_demo": false
    },
    {
      "doc_num": "2026000054883",
      "doc_type": "AH",
      "filed": "2026-04-27",
      "cat": "probate",
      "cat_label": "Affidavit of Heirship",
      "owner": "JONES EARNESTINE",
      "grantee": "HASKELL-VARNER LOURISSIA RHODES DECEASED",
      "amount": null,
      "legal": "Subdivision - Name: CELINA ORIGINAL DONATION Lot: 2 Block: 59 Reference - 1/114",
      "prop_address": "412 E ASH ST",
      "prop_city": "CELINA",
      "prop_state": "TX",
      "prop_zip": "75009",
      "mail_address": "412 E ASH ST",
      "mail_city": "CELINA",
      "mail_state": "TX",
      "mail_zip": "75009-6390",
      "clerk_url": "https://collin.tx.publicsearch.us/results?department=RP&_docTypes=AH&recordedDateRange=20260422,20260429&searchType=advancedSearch",
      "flags": [
        "Probate / estate",
        "New this week"
      ],
      "score": 60,
      "_demo": false
    },
    {
      "doc_num": "2026000054891",
      "doc_type": "AH",
      "filed": "2026-04-27",
      "cat": "probate",
      "cat_label": "Affidavit of Heirship",
      "owner": "ANDREWS LAURA",
      "grantee": "RHODES-COY FLORINEA DECEASED",
      "amount": null,
      "legal": "Subdivision - Name: CELINA ORIGINAL DONATION Lot: 12 Block: 60 Reference - 1/114",
      "prop_address": "3500  VAN ZANDT RD",
      "prop_city": "MELISSA",
      "prop_state": "TX",
      "prop_zip": "75454",
      "mail_address": "3500 VAN ZANDT RD",
      "mail_city": "MELISSA",
      "mail_state": "TX",
      "mail_zip": "75454-2106",
      "clerk_url": "https://collin.tx.publicsearch.us/results?department=RP&_docTypes=AH&recordedDateRange=20260422,20260429&searchType=advancedSearch",
      "flags": [
        "Probate / estate",
        "New this week"
      ],
      "score": 60,
      "_demo": false
    },
    {
      "doc_num": "2026000054889",
      "doc_type": "AH",
      "filed": "2026-04-27",
      "cat": "probate",
      "cat_label": "Affidavit of Heirship",
      "owner": "ANDREWS LAURA MAE",
      "grantee": "RHODES ALEX B SR DECEASED",
      "amount": null,
      "legal": "Subdivision - Name: CELINA ORIGINAL DONATION Lot: 12 Block: 60 Reference - 1/114",
      "prop_address": "3500  VAN ZANDT RD",
      "prop_city": "MELISSA",
      "prop_state": "TX",
      "prop_zip": "75454",
      "mail_address": "3500 VAN ZANDT RD",
      "mail_city": "MELISSA",
      "mail_state": "TX",
      "mail_zip": "75454-2106",
      "clerk_url": "https://collin.tx.publicsearch.us/results?department=RP&_docTypes=AH&recordedDateRange=20260422,20260429&searchType=advancedSearch",
      "flags": [
        "Probate / estate",
        "New this week"
      ],
      "score": 60,
      "_demo": false
    },
    {
      "doc_num": "2026000054887",
      "doc_type": "AH",
      "filed": "2026-04-27",
      "cat": "probate",
      "cat_label": "Affidavit of Heirship",
      "owner": "JONES EARNESTINE",
      "grantee": "VARNER JOE DECEASED",
      "amount": null,
      "legal": "Subdivision - Name: CELINA ORIGINAL DONATION Lot: 4 Block: 59 Reference - 1/114",
      "prop_address": "412 E ASH ST",
      "prop_city": "CELINA",
      "prop_state": "TX",
      "prop_zip": "75009",
      "mail_address": "412 E ASH ST",
      "mail_city": "CELINA",
      "mail_state": "TX",
      "mail_zip": "75009-6390",
      "clerk_url": "https://collin.tx.publicsearch.us/results?department=RP&_docTypes=AH&recordedDateRange=20260422,20260429&searchType=advancedSearch",
      "flags": [
        "Probate / estate",
        "New this week"
      ],
      "score": 60,
      "_demo": false
    },
    {
      "doc_num": "2026000054895",
      "doc_type": "AH",
      "filed": "2026-04-27",
      "cat": "probate",
      "cat_label": "Affidavit of Heirship",
      "owner": "JONES EARNESTINE",
      "grantee": "HASKELL-VARNER LOURISSIA RHODES DECEASED",
      "amount": null,
      "legal": "Subdivision - Name: CELINA ORIGINAL DONATION Lot: 12 Block: 60 Reference - 1/114",
      "prop_address": "412 E ASH ST",
      "prop_city": "CELINA",
      "prop_state": "TX",
      "prop_zip": "75009",
      "mail_address": "412 E ASH ST",
      "mail_city": "CELINA",
      "mail_state": "TX",
      "mail_zip": "75009-6390",
      "clerk_url": "https://collin.tx.publicsearch.us/results?department=RP&_docTypes=AH&recordedDateRange=20260422,20260429&searchType=advancedSearch",
      "flags": [
        "Probate / estate",
        "New this week"
      ],
      "score": 60,
      "_demo": false
    },
    {
      "doc_num": "2026000054893",
      "doc_type": "AH",
      "filed": "2026-04-27",
      "cat": "probate",
      "cat_label": "Affidavit of Heirship",
      "owner": "JONES EARNESTINE",
      "grantee": "RHODES ALEX B SR DECEASED",
      "amount": null,
      "legal": "Subdivision - Name: CELINA ORIGINAL DONATION Lot: 12 Block: 60 Reference - 1/114",
      "prop_address": "412 E ASH ST",
      "prop_city": "CELINA",
      "prop_state": "TX",
      "prop_zip": "75009",
      "mail_address": "412 E ASH ST",
      "mail_city": "CELINA",
      "mail_state": "TX",
      "mail_zip": "75009-6390",
      "clerk_url": "https://collin.tx.publicsearch.us/results?department=RP&_docTypes=AH&recordedDateRange=20260422,20260429&searchType=advancedSearch",
      "flags": [
        "Probate / estate",
        "New this week"
      ],
      "score": 60,
      "_demo": false
    },
    {
      "doc_num": "2026000054894",
      "doc_type": "AH",
      "filed": "2026-04-27",
      "cat": "probate",
      "cat_label": "Affidavit of Heirship",
      "owner": "ANDREWS LAURA",
      "grantee": "RHODES ALEX B JR DECEASED",
      "amount": null,
      "legal": "Subdivision - Name: CELINA ORIGINAL DONATION Lot: 12 Block: 60 Reference - 1/114",
      "prop_address": "3500  VAN ZANDT RD",
      "prop_city": "MELISSA",
      "prop_state": "TX",
      "prop_zip": "75454",
      "mail_address": "3500 VAN ZANDT RD",
      "mail_city": "MELISSA",
      "mail_state": "TX",
      "mail_zip": "75454-2106",
      "clerk_url": "https://collin.tx.publicsearch.us/results?department=RP&_docTypes=AH&recordedDateRange=20260422,20260429&searchType=advancedSearch",
      "flags": [
        "Probate / estate",
        "New this week"
      ],
      "score": 60,
      "_demo": false
    },
    {
      "doc_num": "2026000054890",
      "doc_type": "AH",
      "filed": "2026-04-27",
      "cat": "probate",
      "cat_label": "Affidavit of Heirship",
      "owner": "ANDREWS LAURA",
      "grantee": "VARNER JOE DECEASED",
      "amount": null,
      "legal": "Subdivision - Name: CELINA ORIGINAL DONATION Lot: 4 Block: 59 Reference - 1/114",
      "prop_address": "3500  VAN ZANDT RD",
      "prop_city": "MELISSA",
      "prop_state": "TX",
      "prop_zip": "75454",
      "mail_address": "3500 VAN ZANDT RD",
      "mail_city": "MELISSA",
      "mail_state": "TX",
      "mail_zip": "75454-2106",
      "clerk_url": "https://collin.tx.publicsearch.us/results?department=RP&_docTypes=AH&recordedDateRange=20260422,20260429&searchType=advancedSearch",
      "flags": [
        "Probate / estate",
        "New this week"
      ],
      "score": 60,
      "_demo": false
    },
    {
      "doc_num": "2026000054780",
      "doc_type": "AH",
      "filed": "2026-04-27",
      "cat": "probate",
      "cat_label": "Affidavit of Heirship",
      "owner": "VOKOLEK VERONICA R",
      "grantee": "VOKOLEK GERALD DECEASED",
      "amount": null,
      "legal": "Subdivision - Name: SPRING CK PKWY EST W 8 PL Lot: 21 Block: D Reference - B/339",
      "prop_address": "2412  BRYCEWOOD LN",
      "prop_city": "PLANO",
      "prop_state": "TX",
      "prop_zip": "75025",
      "mail_address": "3517 TERRY DR",
      "mail_city": "PLANO",
      "mail_state": "TX",
      "mail_zip": "75023-1132",
      "clerk_url": "https://collin.tx.publicsearch.us/results?department=RP&_docTypes=AH&recordedDateRange=20260422,20260429&searchType=advancedSearch",
      "flags": [
        "Probate / estate",
        "New this week"
      ],
      "score": 60,
      "_demo": false
    },
    {
      "doc_num": "2026000054888",
      "doc_type": "AH",
      "filed": "2026-04-27",
      "cat": "probate",
      "cat_label": "Affidavit of Heirship",
      "owner": "JONES EARNESTINE",
      "grantee": "RHODES ALEX B JR DECEASED",
      "amount": null,
      "legal": "Subdivision - Name: CELINA ORIGINAL DONATION Lot: 12 Block: 60 Reference - 1/114",
      "prop_address": "412 E ASH ST",
      "prop_city": "CELINA",
      "prop_state": "TX",
      "prop_zip": "75009",
      "mail_address": "412 E ASH ST",
      "mail_city": "CELINA",
      "mail_state": "TX",
      "mail_zip": "75009-6390",
      "clerk_url": "https://collin.tx.publicsearch.us/results?department=RP&_docTypes=AH&recordedDateRange=20260422,20260429&searchType=advancedSearch",
      "flags": [
        "Probate / estate",
        "New this week"
      ],
      "score": 60,
      "_demo": false
    },
    {
      "doc_num": "2026000054884",
      "doc_type": "AH",
      "filed": "2026-04-27",
      "cat": "probate",
      "cat_label": "Affidavit of Heirship",
      "owner": "ANDREWS LAURA",
      "grantee": "RHODES ROBERT L DECEASED",
      "amount": null,
      "legal": "Subdivision - Name: CELINA ORIGINAL DONATION Lot: 12 Block: 60 Reference - 1/114",
      "prop_address": "3500  VAN ZANDT RD",
      "prop_city": "MELISSA",
      "prop_state": "TX",
      "prop_zip": "75454",
      "mail_address": "3500 VAN ZANDT RD",
      "mail_city": "MELISSA",
      "mail_state": "TX",
      "mail_zip": "75454-2106",
      "clerk_url": "https://collin.tx.publicsearch.us/results?department=RP&_docTypes=AH&recordedDateRange=20260422,20260429&searchType=advancedSearch",
      "flags": [
        "Probate / estate",
        "New this week"
      ],
      "score": 60,
      "_demo": false
    },
    {
      "doc_num": "2026000054892",
      "doc_type": "AH",
      "filed": "2026-04-27",
      "cat": "probate",
      "cat_label": "Affidavit of Heirship",
      "owner": "JONES EARNESTINE",
      "grantee": "RHODES-COY FLORINEA DECEASED",
      "amount": null,
      "legal": "Subdivision - Name: CELINA ORIGINAL DONATION Lot: 12 Block: 60 Reference - 1/114",
      "prop_address": "412 E ASH ST",
      "prop_city": "CELINA",
      "prop_state": "TX",
      "prop_zip": "75009",
      "mail_address": "412 E ASH ST",
      "mail_city": "CELINA",
      "mail_state": "TX",
      "mail_zip": "75009-6390",
      "clerk_url": "https://collin.tx.publicsearch.us/results?department=RP&_docTypes=AH&recordedDateRange=20260422,20260429&searchType=advancedSearch",
      "flags": [
        "Probate / estate",
        "New this week"
      ],
      "score": 60,
      "_demo": false
    },
    {
      "doc_num": "2026000054882",
      "doc_type": "AH",
      "filed": "2026-04-27",
      "cat": "probate",
      "cat_label": "Affidavit of Heirship",
      "owner": "ANDREWS LAURA",
      "grantee": "HASKELL-VARNER LOURISSIA RHODES DECEASED",
      "amount": null,
      "legal": "Subdivision - Name: CELINA ORIGINAL DONATION Lot: 2 Block: 59 Reference - 1/114",
      "prop_address": "3500  VAN ZANDT RD",
      "prop_city": "MELISSA",
      "prop_state": "TX",
      "prop_zip": "75454",
      "mail_address": "3500 VAN ZANDT RD",
      "mail_city": "MELISSA",
      "mail_state": "TX",
      "mail_zip": "75454-2106",
      "clerk_url": "https://collin.tx.publicsearch.us/results?department=RP&_docTypes=AH&recordedDateRange=20260422,20260429&searchType=advancedSearch",
      "flags": [
        "Probate / estate",
        "New this week"
      ],
      "score": 60,
      "_demo": false
    },
    {
      "doc_num": "2026000054714",
      "doc_type": "LIEN",
      "filed": "2026-04-27",
      "cat": "lien",
      "cat_label": "Lien",
      "owner": "TRIVEDI TUSHAR",
      "grantee": "CAMBRIDGE PLACE AT RUSSELL CREEK HOMEOWNERS ASN INC",
      "amount": null,
      "legal": "Subdivision - Name: CAMBRIDGE PL RUSSELL CR PL Lot: 18 Block: B Reference - N/928",
      "prop_address": "2328  HOMESTEAD LN",
      "prop_city": "PLANO",
      "prop_state": "TX",
      "prop_zip": "75025",
      "mail_address": "2328 HOMESTEAD LN",
      "mail_city": "PLANO",
      "mail_state": "TX",
      "mail_zip": "75025-5526",
      "clerk_url": "https://collin.tx.publicsearch.us/results?department=RP&_docTypes=LIEN&recordedDateRange=20260422,20260429&searchType=advancedSearch",
      "flags": [
        "Lien",
        "New this week"
      ],
      "score": 60,
      "_demo": false
    },
    {
      "doc_num": "2026000054753",
      "doc_type": "LIEN",
      "filed": "2026-04-27",
      "cat": "lien",
      "cat_label": "Lien",
      "owner": "POLLACIA FRANK W",
      "grantee": "CAMBRIDGE PLACE AT RUSSELL CREEK HOMEOWNERS ASN INC",
      "amount": null,
      "legal": "Subdivision - Name: CAMBRIDGE PL RUSSELL CR PL Lot: 19 Block: D Reference - N/928",
      "prop_address": "1123  SOPHIA ST",
      "prop_city": "ALLEN",
      "prop_state": "TX",
      "prop_zip": "75013",
      "mail_address": "1123 SOPHIA ST",
      "mail_city": "ALLEN",
      "mail_state": "TX",
      "mail_zip": "75013-4928",
      "clerk_url": "https://collin.tx.publicsearch.us/results?department=RP&_docTypes=LIEN&recordedDateRange=20260422,20260429&searchType=advancedSearch",
      "flags": [
        "Lien",
        "New this week"
      ],
      "score": 60,
      "_demo": false
    },
    {
      "doc_num": "2026000054577",
      "doc_type": "LIEN",
      "filed": "2026-04-27",
      "cat": "lien",
      "cat_label": "Lien",
      "owner": "WILLIAMS SPRING A",
      "grantee": "COVENANT CLEARINGHOUSE LLC TRUSTEE",
      "amount": null,
      "legal": "Subdivision - Name: CREEKSIDE ESTATES #7 WYLIE Lot: 19 Block: S Reference - 2015/45",
      "prop_address": "1642  JEFFREY DR",
      "prop_city": "WYLIE",
      "prop_state": "TX",
      "prop_zip": "75098",
      "mail_address": "1642 JEFFREY DR",
      "mail_city": "WYLIE",
      "mail_state": "TX",
      "mail_zip": "75098-8929",
      "clerk_url": "https://collin.tx.publicsearch.us/results?department=RP&_docTypes=LIEN&recordedDateRange=20260422,20260429&searchType=advancedSearch",
      "flags": [
        "Lien",
        "New this week"
      ],
      "score": 60,
      "_demo": false
    },
    {
      "doc_num": "2026000054572",
      "doc_type": "LIEN",
      "filed": "2026-04-27",
      "cat": "lien",
      "cat_label": "Lien",
      "owner": "SHASHEE BALA",
      "grantee": "COVENANT CLEARINGHOUSE LLC TRUSTEE",
      "amount": null,
      "legal": "Subdivision - Name: TRAILS AT RIVERSTONE 5 Lot: 23 Block: H",
      "prop_address": "608  RUSTIC MEADOWS TRL",
      "prop_city": "PRINCETON",
      "prop_state": "TX",
      "prop_zip": "75407",
      "mail_address": "608 RUSTIC MEADOWS TRL",
      "mail_city": "PRINCETON",
      "mail_state": "TX",
      "mail_zip": "75407-2294",
      "clerk_url": "https://collin.tx.publicsearch.us/results?department=RP&_docTypes=LIEN&recordedDateRange=20260422,20260429&searchType=advancedSearch",
      "flags": [
        "Lien",
        "New this week"
      ],
      "score": 60,
      "_demo": false
    },
    {
      "doc_num": "2026000054727",
      "doc_type": "LIEN",
      "filed": "2026-04-27",
      "cat": "lien",
      "cat_label": "Lien",
      "owner": "BEATY KAREN",
      "grantee": "RUTH CONSULTING",
      "amount": null,
      "legal": "Survey - Name: G MORRISON SUR Survey: 559 Acres: .24",
      "prop_address": "230 E FIFTH ST",
      "prop_city": "ANNA",
      "prop_state": "TX",
      "prop_zip": "75409",
      "mail_address": "230 E 5TH ST",
      "mail_city": "ANNA",
      "mail_state": "TX",
      "mail_zip": "75409-2608",
      "clerk_url": "https://collin.tx.publicsearch.us/results?department=RP&_docTypes=LIEN&recordedDateRange=20260422,20260429&searchType=advancedSearch",
      "flags": [
        "Lien",
        "New this week"
      ],
      "score": 60,
      "_demo": false
    },
    {
      "doc_num": "2026000054737",
      "doc_type": "LIEN",
      "filed": "2026-04-27",
      "cat": "lien",
      "cat_label": "Lien",
      "owner": "GUPTA PAWAN",
      "grantee": "CAMBRIDGE PLACE AT RUSSELL CREEK HOMEOWNERS ASN INC",
      "amount": null,
      "legal": "Subdivision - Name: CAMBRIDGE PL RUSSELL CR PL Lot: 16 Block: H Reference - N/928",
      "prop_address": "1504  MINERAL POINT PL",
      "prop_city": "MELISSA",
      "prop_state": "TX",
      "prop_zip": "75454",
      "mail_address": "1504 MINERAL POINT PL",
      "mail_city": "MELISSA",
      "mail_state": "TX",
      "mail_zip": "75454-2830",
      "clerk_url": "https://collin.tx.publicsearch.us/results?department=RP&_docTypes=LIEN&recordedDateRange=20260422,20260429&searchType=advancedSearch",
      "flags": [
        "Lien",
        "New this week"
      ],
      "score": 60,
      "_demo": false
    },
    {
      "doc_num": "2026000054721",
      "doc_type": "LIEN",
      "filed": "2026-04-27",
      "cat": "lien",
      "cat_label": "Lien",
      "owner": "AGAV SAR",
      "grantee": "FRISCO PRESTON HILLS HOMEOWNERS ASN INC",
      "amount": null,
      "legal": "Subdivision - Name: PRESTON HILLS ADDITION #1 FRISCO Lot: 7 Block: N Reference - 2016/519",
      "prop_address": "15439  CARNOUSTIE LN",
      "prop_city": "FRISCO",
      "prop_state": "TX",
      "prop_zip": "75035",
      "mail_address": "15439 CARNOUSTIE LN",
      "mail_city": "FRISCO",
      "mail_state": "TX",
      "mail_zip": "75035-1041",
      "clerk_url": "https://collin.tx.publicsearch.us/results?department=RP&_docTypes=LIEN&recordedDateRange=20260422,20260429&searchType=advancedSearch",
      "flags": [
        "Lien",
        "New this week"
      ],
      "score": 60,
      "_demo": false
    },
    {
      "doc_num": "2026000054810",
      "doc_type": "LIEN",
      "filed": "2026-04-27",
      "cat": "lien",
      "cat_label": "Lien",
      "owner": "SANDERS DANASHA",
      "grantee": "MORNINGSTAR MEADOW HOMEOWNERS ASN INC",
      "amount": null,
      "legal": "Subdivision - Name: PASQUINELLIS MORNINGSTAR MEADOW Lot: 36 Block: A",
      "prop_address": "4108  KYNDRA CIR",
      "prop_city": "RICHARDSON",
      "prop_state": "TX",
      "prop_zip": "75082",
      "mail_address": "4108 KYNDRA CIR",
      "mail_city": "RICHARDSON",
      "mail_state": "TX",
      "mail_zip": "75082-2761",
      "clerk_url": "https://collin.tx.publicsearch.us/results?department=RP&_docTypes=LIEN&recordedDateRange=20260422,20260429&searchType=advancedSearch",
      "flags": [
        "Lien",
        "New this week"
      ],
      "score": 60,
      "_demo": false
    },
    {
      "doc_num": "2026000054724",
      "doc_type": "LIEN",
      "filed": "2026-04-27",
      "cat": "lien",
      "cat_label": "Lien",
      "owner": "GOEL PARAS",
      "grantee": "THOMAS RAJA",
      "amount": null,
      "legal": "Subdivision - Name: PANTHER CREEK ESTATES 1 2 3 4 5 & 6",
      "prop_address": "4589  JAGUAR DR",
      "prop_city": "PLANO",
      "prop_state": "TX",
      "prop_zip": "75024",
      "mail_address": "4589 JAGUAR DR",
      "mail_city": "PLANO",
      "mail_state": "TX",
      "mail_zip": "75024-3987",
      "clerk_url": "https://collin.tx.publicsearch.us/results?department=RP&_docTypes=LIEN&recordedDateRange=20260422,20260429&searchType=advancedSearch",
      "flags": [
        "Lien",
        "New this week"
      ],
      "score": 60,
      "_demo": false
    },
    {
      "doc_num": "2026000054687",
      "doc_type": "LIEN",
      "filed": "2026-04-27",
      "cat": "lien",
      "cat_label": "Lien",
      "owner": "S2 PRESTON PARK LP",
      "grantee": "RASA FLOORS & CARPET CLEANING LLC",
      "amount": null,
      "legal": "Subdivision - Name: BISHOPS GATE Lot: 1 Block: A",
      "prop_address": "4701  PRESTON PARK BLVD",
      "prop_city": "PLANO",
      "prop_state": "TX",
      "prop_zip": "75093",
      "mail_address": "5950 BERKSHIRE LN STE 1300",
      "mail_city": "DALLAS",
      "mail_state": "TX",
      "mail_zip": "75225-5841",
      "clerk_url": "https://collin.tx.publicsearch.us/results?department=RP&_docTypes=LIEN&recordedDateRange=20260422,20260429&searchType=advancedSearch",
      "flags": [
        "Lien",
        "New this week"
      ],
      "score": 60,
      "_demo": false
    },
    {
      "doc_num": "2026000054643",
      "doc_type": "LIEN",
      "filed": "2026-04-27",
      "cat": "lien",
      "cat_label": "Lien",
      "owner": "ESTRIDGE VIVIAN AILEEN",
      "grantee": "HRP HOMEOWNERS ASN INC",
      "amount": null,
      "legal": "Subdivision - Name: HIGHLANDS RUSSELL PK #1 PL Lot: 7 Block: A Reference - K/107",
      "prop_address": "3404  SAN PATRICIO DR",
      "prop_city": "PLANO",
      "prop_state": "TX",
      "prop_zip": "75025",
      "mail_address": "3404 SAN PATRICIO DR",
      "mail_city": "PLANO",
      "mail_state": "TX",
      "mail_zip": "75025-4550",
      "clerk_url": "https://collin.tx.publicsearch.us/results?department=RP&_docTypes=LIEN&recordedDateRange=20260422,20260429&searchType=advancedSearch",
      "flags": [
        "Lien",
        "New this week"
      ],
      "score": 60,
      "_demo": false
    },
    {
      "doc_num": "2026000054652",
      "doc_type": "LIEN",
      "filed": "2026-04-27",
      "cat": "lien",
      "cat_label": "Lien",
      "owner": "PARRISH TED",
      "grantee": "PRESTON VILLAGE I ASN INC",
      "amount": null,
      "legal": "Subdivision - Name: PRESTON VILLAGE 4 Lot: 109 Block: J",
      "prop_address": "6601  KNOLLWOOD DR",
      "prop_city": "MCKINNEY",
      "prop_state": "TX",
      "prop_zip": "75072",
      "mail_address": "6601 KNOLLWOOD DR",
      "mail_city": "MCKINNEY",
      "mail_state": "TX",
      "mail_zip": "75072-2360",
      "clerk_url": "https://collin.tx.publicsearch.us/results?department=RP&_docTypes=LIEN&recordedDateRange=20260422,20260429&searchType=advancedSearch",
      "flags": [
        "Lien",
        "New this week"
      ],
      "score": 60,
      "_demo": false
    },
    {
      "doc_num": "2026000055571",
      "doc_type": "AJ",
      "filed": "2026-04-28",
      "cat": "judgment",
      "cat_label": "Abstract of Judgment",
      "owner": "Alexander Scott A.",
      "grantee": "Assoc Stonebridge Ranch Community",
      "amount": null,
      "legal": "N/A",
      "prop_address": "6807  SHOREVIEW DR",
      "prop_city": "MCKINNEY",
      "prop_state": "TX",
      "prop_zip": "75072",
      "mail_address": "6807 SHOREVIEW DR",
      "mail_city": "MCKINNEY",
      "mail_state": "TX",
      "mail_zip": "75072-5596",
      "clerk_url": "https://collin.tx.publicsearch.us/results?department=RP&_docTypes=AJ&recordedDateRange=20260422,20260429&searchType=advancedSearch",
      "flags": [
        "Judgment lien",
        "New this week"
      ],
      "score": 60,
      "_demo": false
    },
    {
      "doc_num": "2026000055546",
      "doc_type": "AH",
      "filed": "2026-04-28",
      "cat": "probate",
      "cat_label": "Affidavit of Heirship",
      "owner": "Phillips Joanna Jostings",
      "grantee": "Rollins Michele Lee",
      "amount": null,
      "legal": "N/A",
      "prop_address": "5005  TIMBER CIRCLE DR",
      "prop_city": "MCKINNEY",
      "prop_state": "TX",
      "prop_zip": "75072",
      "mail_address": "5005 TIMBER CIRCLE DR",
      "mail_city": "MCKINNEY",
      "mail_state": "TX",
      "mail_zip": "75072-5393",
      "clerk_url": "https://collin.tx.publicsearch.us/results?department=RP&_docTypes=AH&recordedDateRange=20260422,20260429&searchType=advancedSearch",
      "flags": [
        "Probate / estate",
        "New this week"
      ],
      "score": 60,
      "_demo": false
    },
    {
      "doc_num": "2026000055365",
      "doc_type": "LIEN",
      "filed": "2026-04-28",
      "cat": "lien",
      "cat_label": "Lien",
      "owner": "Tonu Maxim",
      "grantee": "Pecan Park Owners Association, Inc.",
      "amount": null,
      "legal": "N/A",
      "prop_address": "4305  PECAN KNOLL DR",
      "prop_city": "MCKINNEY",
      "prop_state": "TX",
      "prop_zip": "75070",
      "mail_address": "4305 PECAN KNOLL DR",
      "mail_city": "MCKINNEY",
      "mail_state": "TX",
      "mail_zip": "75070-1015",
      "clerk_url": "https://collin.tx.publicsearch.us/results?department=RP&_docTypes=LIEN&recordedDateRange=20260422,20260429&searchType=advancedSearch",
      "flags": [
        "Lien",
        "New this week"
      ],
      "score": 60,
      "_demo": false
    },
    {
      "doc_num": "2026000055363",
      "doc_type": "LIEN",
      "filed": "2026-04-28",
      "cat": "lien",
      "cat_label": "Lien",
      "owner": "Vishnubhotla Krishna",
      "grantee": "Pecan Park Owners Association, Inc.",
      "amount": null,
      "legal": "N/A",
      "prop_address": "4225  BLACKJACK OAK DR",
      "prop_city": "MCKINNEY",
      "prop_state": "TX",
      "prop_zip": "75070",
      "mail_address": "4225 BLACKJACK OAK DR",
      "mail_city": "MCKINNEY",
      "mail_state": "TX",
      "mail_zip": "75070-1012",
      "clerk_url": "https://collin.tx.publicsearch.us/results?department=RP&_docTypes=LIEN&recordedDateRange=20260422,20260429&searchType=advancedSearch",
      "flags": [
        "Lien",
        "New this week"
      ],
      "score": 60,
      "_demo": false
    }
  ]
}